pysvn/__init__.py
pysvn/client.py
pysvn-0.1.0.dist-info/LICENSE
pysvn-0.1.0.dist-info/METADATA
pysvn-0.1.0.dist-info/WHEEL
pysvn-0.1.0.dist-info/top_level.txt
pysvn-0.1.0.dist-info/RECORD
