Metadata-Version: 2.1
Name: pysvn
Version: 0.1.0
Summary: Svn for python.
Home-page: https://github.com/leafvmaple/pysvn
Author: Zohar Lee
Author-email: leafvmaple@gmail.com
License: BSD License
Keywords: svn,pysvn
Platform: any
Classifier: Operating System :: OS Independent
Classifier: Programming Language :: Python :: 3
Classifier: License :: OSI Approved :: BSD License
Classifier: Development Status :: 4 - Beta
